arcle/__init__.py
arcle/actions/__init__.py
arcle/actions/color.py
arcle/actions/critical.py
arcle/actions/object.py
arcle/arcs/ARC/.git
arcle/arcs/ARC/data/evaluation/00576224.json
arcle/arcs/ARC/data/evaluation/009d5c81.json
arcle/arcs/ARC/data/evaluation/00dbd492.json
arcle/arcs/ARC/data/evaluation/03560426.json
arcle/arcs/ARC/data/evaluation/05a7bcf2.json
arcle/arcs/ARC/data/evaluation/0607ce86.json
arcle/arcs/ARC/data/evaluation/0692e18c.json
arcle/arcs/ARC/data/evaluation/070dd51e.json
arcle/arcs/ARC/data/evaluation/08573cc6.json
arcle/arcs/ARC/data/evaluation/0934a4d8.json
arcle/arcs/ARC/data/evaluation/09c534e7.json
arcle/arcs/ARC/data/evaluation/0a1d4ef5.json
arcle/arcs/ARC/data/evaluation/0a2355a6.json
arcle/arcs/ARC/data/evaluation/0b17323b.json
arcle/arcs/ARC/data/evaluation/0bb8deee.json
arcle/arcs/ARC/data/evaluation/0becf7df.json
arcle/arcs/ARC/data/evaluation/0c786b71.json
arcle/arcs/ARC/data/evaluation/0c9aba6e.json
arcle/arcs/ARC/data/evaluation/0d87d2a6.json
arcle/arcs/ARC/data/evaluation/0e671a1a.json
arcle/arcs/ARC/data/evaluation/0f63c0b9.json
arcle/arcs/ARC/data/evaluation/103eff5b.json
arcle/arcs/ARC/data/evaluation/11e1fe23.json
arcle/arcs/ARC/data/evaluation/12422b43.json
arcle/arcs/ARC/data/evaluation/12997ef3.json
arcle/arcs/ARC/data/evaluation/12eac192.json
arcle/arcs/ARC/data/evaluation/136b0064.json
arcle/arcs/ARC/data/evaluation/13713586.json
arcle/arcs/ARC/data/evaluation/137f0df0.json
arcle/arcs/ARC/data/evaluation/140c817e.json
arcle/arcs/ARC/data/evaluation/14754a24.json
arcle/arcs/ARC/data/evaluation/15113be4.json
arcle/arcs/ARC/data/evaluation/15663ba9.json
arcle/arcs/ARC/data/evaluation/15696249.json
arcle/arcs/ARC/data/evaluation/16b78196.json
arcle/arcs/ARC/data/evaluation/17b80ad2.json
arcle/arcs/ARC/data/evaluation/17cae0c1.json
arcle/arcs/ARC/data/evaluation/18419cfa.json
arcle/arcs/ARC/data/evaluation/184a9768.json
arcle/arcs/ARC/data/evaluation/195ba7dc.json
arcle/arcs/ARC/data/evaluation/1990f7a8.json
arcle-0.2.6.dist-info/METADATA
arcle-0.2.6.dist-info/WHEEL
arcle-0.2.6.dist-info/RECORD
