Metadata-Version: 2.1
Name: arcle
Version: 0.2.6
Summary: An ARC Learning Environment built on Gymnasium
Home-page: https://github.com/ConfeitoHS/arcle
License: Apache-2.0
Author: Hosung Lee
Author-email: confeitohs@gmail.com
Requires-Python: >=3.8
Classifier: Development Status :: 3 - Alpha
Classifier: License :: OSI Approved :: Apache Software License
Classifier: Programming Language :: Python :: 3
Classifier: Programming Language :: Python :: 3.8
Classifier: Programming Language :: Python :: 3.9
Classifier: Programming Language :: Python :: 3.10
Classifier: Programming Language :: Python :: 3.11
Classifier: Programming Language :: Python :: 3.12
Classifier: Topic :: Scientific/Engineering :: Artificial Intelligence
Requires-Dist: gymnasium (>=0.28.0)
Requires-Dist: numpy (>=1.24)
Requires-Dist: pygame (>=2.5.1,<3.0.0)
Project-URL: Bug Tracker, https://github.com/ConfeitoHS/arcle/issues
Project-URL: Repository, https://github.com/ConfeitoHS/arcle
